py_yuwinzer_server-0.3.14.data/scripts/server_run
server/__init__.py
server/launcher_for_ubuntu.py
server/launcher_for_windows.py
server/start_server.py
server/common/__init__.py
server/common/errors.py
server/common/globals.py
server/common/utils.py
server/log/__init__.py
server/log/decorator.py
server/log/server_log_config.py
server/server/__init__.py
server/server/server_core.py
server/server/server_db.py
server/server/server_gui.py
server/unit_tests/__init__.py
server/unit_tests/test_client.py
server/unit_tests/test_server.py
server/unit_tests/test_utils.py
py_yuwinzer_server-0.3.14.dist-info/METADATA
py_yuwinzer_server-0.3.14.dist-info/WHEEL
py_yuwinzer_server-0.3.14.dist-info/top_level.txt
py_yuwinzer_server-0.3.14.dist-info/RECORD
