Metadata-Version: 2.1
Name: py-yuwinzer-server
Version: 0.3.14
Summary: Yuwinzer Server
Home-page: UNKNOWN
Author: Sary Petrova
Author-email: test_t@gmail.com
License: UNKNOWN
Platform: UNKNOWN
Requires-Dist: PyQt5
Requires-Dist: sqlalchemy
Requires-Dist: pycryptodome
Requires-Dist: pycryptodomex
